zenquotespy/__init__.py
zenquotespy/main.py
zenquotespy-1.0.0.dist-info/licenses/LICENSE
zenquotespy-1.0.0.dist-info/METADATA
zenquotespy-1.0.0.dist-info/WHEEL
zenquotespy-1.0.0.dist-info/top_level.txt
zenquotespy-1.0.0.dist-info/RECORD
