Metadata-Version: 2.4
Name: zenquotespy
Version: 1.0.0
Summary: ZenquotesPy is a lightweight Python package that provides easy access to motivational and inspirational quotes from the ZenQuotes.io API.
Home-page: https://zenquotespy.pages.dev
Author: Nilay Sarma
License: MIT
Project-URL: Documentation, https://zenquotespy.pages.dev/getting-started
Project-URL: Repository, https://github.com/nilaysarma/zenquotespy
Project-URL: Release Notes, https://github.com/nilaysarma/zenquotespy/releases/latest
Classifier: Development Status :: 5 - Production/Stable
Classifier: Intended Audience :: Developers
Classifier: Intended Audience :: Education
Classifier: License :: OSI Approved :: MIT License
Classifier: Operating System :: OS Independent
Classifier: Programming Language :: Python :: 3
Classifier: Topic :: Software Development :: Libraries :: Python Modules
License-File: LICENSE
Requires-Dist: requests==2.32.3
Dynamic: author
Dynamic: classifier
Dynamic: description
Dynamic: description-content-type
Dynamic: home-page
Dynamic: license
Dynamic: license-file
Dynamic: project-url
Dynamic: requires-dist
Dynamic: summary
